{
	"apiVersion": 3,
	"name": "andstudio/strategy-7",
	"title": "strategy-7",
	"description": "strategy-7 block",
	"style": ["file:./strategy-7.css"],
	"category": "strategy",
	"icon": "admin-comments",
	"keywords": ["andstudio", "strategy-7"],
	"acf": {
		"renderTemplate": "strategy-7.php",
		"blockVersion": 3
	},
	"supports": {
		"anchor": false
	},
 "example": {
        "attributes": {
            "mode": "preview",
            "data": {
                "preview_image": "preview.jpg"
            }
        }
}
}
